LICENSE.md
MANIFEST.in
README.md
dynamic_extras_require.txt
dynamic_install_requires.txt
quicklib_incorporated.v2.4.zip
quicklib_setup_from_yml.py
epic/caching/__init__.py
epic/caching/__version__.py
epic/caching/_cache.py
epic/caching/cached.py
epic/caching/property.py
epic/caching/singleton.py
epic/caching/tests/__init__.py
epic/caching/tests/test_caching.py
epic_caching.egg-info/PKG-INFO
epic_caching.egg-info/SOURCES.txt
epic_caching.egg-info/dependency_links.txt
epic_caching.egg-info/requires.txt
epic_caching.egg-info/top_level.txt